spatial_tda/__init__.py
spatial_tda/adjacency_simplex.py
spatial_tda/calculate_tda_summaries.py
spatial_tda/common.py
spatial_tda/invr.py
spatial_tda/plot_utills.py
spatial_tda/spatial_tda.py
spatial_tda-0.0.9.dist-info/LICENSE
spatial_tda-0.0.9.dist-info/METADATA
spatial_tda-0.0.9.dist-info/WHEEL
spatial_tda-0.0.9.dist-info/entry_points.txt
spatial_tda-0.0.9.dist-info/top_level.txt
spatial_tda-0.0.9.dist-info/RECORD
