Metadata-Version: 2.2
Name: spatial-tda
Version: 0.0.9
Summary: Python Boilerplate contains all the boilerplate you need to create a Python package.
Author-email: Hashan Fernando <hashan.dan@gmail.com>
License: MIT License
Project-URL: Homepage, https://github.com/hashansl/spatial-tda
Keywords: spatial-tda
Classifier: Intended Audience :: Developers
Classifier: License :: OSI Approved :: MIT License
Classifier: Natural Language :: English
Classifier: Programming Language :: Python :: 3.8
Classifier: Programming Language :: Python :: 3.9
Classifier: Programming Language :: Python :: 3.10
Classifier: Programming Language :: Python :: 3.11
Classifier: Programming Language :: Python :: 3.12
Requires-Python: >=3.8
License-File: LICENSE
Requires-Dist: numpy
Requires-Dist: geopandas
Requires-Dist: pandas
Provides-Extra: all
Requires-Dist: spatial-tda[extra]; extra == "all"
Provides-Extra: extra
Requires-Dist: pandas; extra == "extra"
